screenuler/__init__.py
screenuler/app.py
screenuler/helpers.py
screenuler-0.1.4.dist-info/LICENSE
screenuler-0.1.4.dist-info/METADATA
screenuler-0.1.4.dist-info/WHEEL
screenuler-0.1.4.dist-info/entry_points.txt
screenuler-0.1.4.dist-info/top_level.txt
screenuler-0.1.4.dist-info/RECORD
