Metadata-Version: 2.1
Name: screenuler
Version: 0.1.4
Summary: Simple Python Tkinter screen ruler
Author: vkalyvayut-roboty-a-ne-chelovek
License: This is free and unencumbered software released into the public domain.
Project-URL: Homepage, https://github.com/vkalyvayut-roboty-a-ne-chelovek/screenuler
Project-URL: Issues, https://github.com/vkalyvayut-roboty-a-ne-chelovek/screenuler/issues
Classifier: Programming Language :: Python
Classifier: Development Status :: 4 - Beta
Classifier: Intended Audience :: End Users/Desktop
Classifier: License :: OSI Approved :: The Unlicense (Unlicense)
Classifier: Operating System :: OS Independent
Requires-Python: >=3.10
License-File: LICENSE
Requires-Dist: miros
